nanotron/__init__.py
nanotron/constants.py
nanotron/dataloader.py
nanotron/distributed.py
nanotron/helpers.py
nanotron/logging.py
nanotron/random.py
nanotron/sanity_checks.py
nanotron/trainer.py
nanotron/utils.py
nanotron/config/__init__.py
nanotron/config/config.py
nanotron/config/lighteval_config.py
nanotron/config/models_config.py
nanotron/config/parallelism_config.py
nanotron/config/utils_config.py
nanotron/fp8/__init__.py
nanotron/fp8/constants.py
nanotron/fp8/dtypes.py
nanotron/fp8/kernel.py
nanotron/fp8/linear.py
nanotron/fp8/meta.py
nanotron/fp8/parameter.py
nanotron/fp8/tensor.py
nanotron/fp8/utils.py
nanotron/generation/__init__.py
nanotron/generation/decode.py
nanotron/generation/generate_store.py
nanotron/generation/sampler.py
nanotron/models/__init__.py
nanotron/models/base.py
nanotron/models/llama.py
nanotron/models/starcoder2.py
nanotron/nn/__init__.py
nanotron/nn/activations.py
nanotron/nn/layer_norm.py
nanotron/optim/__init__.py
nanotron/optim/base.py
nanotron/optim/clip_grads.py
nanotron/optim/gradient_accumulator.py
nanotron/optim/inherit_from_other_optimizer.py
nanotron/optim/named_optimizer.py
nanotron/optim/optimizer_from_gradient_accumulator.py
nanotron/optim/zero.py
nanotron/parallel/__init__.py
nanotron/parallel/context.py
nanotron/parallel/parameters.py
nanotron/parallel/sharded_parameters.py
nanotron/parallel/tied_parameters.py
nanotron/parallel/utils.py
nanotron/parallel/data_parallel/utils.py
nanotron/parallel/pipeline_parallel/__init__.py
nanotron/parallel/pipeline_parallel/block.py
nanotron/parallel/pipeline_parallel/context_manager.py
nanotron/parallel/pipeline_parallel/engine.py
nanotron/parallel/pipeline_parallel/functional.py
nanotron/parallel/pipeline_parallel/p2p.py
nanotron/parallel/pipeline_parallel/state.py
nanotron/parallel/pipeline_parallel/tensor_pointer.py
nanotron/parallel/pipeline_parallel/utils.py
nanotron/parallel/tensor_parallel/__init__.py
nanotron/parallel/tensor_parallel/distributed_differentiable_primitives.py
nanotron-0.4.dist-info/LICENSE
nanotron-0.4.dist-info/METADATA
nanotron-0.4.dist-info/WHEEL
nanotron-0.4.dist-info/top_level.txt
nanotron-0.4.dist-info/RECORD
