Metadata-Version: 2.1
Name: nanotron
Version: 0.4
Summary: Minimalistic Large Language Model Training and Finetuning
Author-email: Nouamane Tazi <nouamane@huggingface.co>, Thomas Wang <thomas.wang@huggingface.co>, Kunhao Zheng <kunhao@huggingface.co>, Thomas Wolf <thomas@huggingface.co>
Classifier: Topic :: Software Development
Requires-Python: ~=3.10
License-File: LICENSE
Requires-Dist: torch >=1.13.1
Requires-Dist: pyyaml
Requires-Dist: numpy
Requires-Dist: packaging
Requires-Dist: safetensors
Requires-Dist: dacite
Requires-Dist: tqdm
Provides-Extra: dev
Requires-Dist: pre-commit ; extra == 'dev'
Requires-Dist: pylint ; extra == 'dev'
Provides-Extra: fast-modeling
Requires-Dist: flash-attn >=2.5.0 ; extra == 'fast-modeling'
Provides-Extra: test
Requires-Dist: pytest ; extra == 'test'
Requires-Dist: pytest-xdist ; extra == 'test'
